odoo/addons/ssi_psychology_evaluation/README.rst
odoo/addons/ssi_psychology_evaluation/__init__.py
odoo/addons/ssi_psychology_evaluation/__manifest__.py
odoo/addons/ssi_psychology_evaluation/menu.xml
odoo/addons/ssi_psychology_evaluation/data/approval_template_data.xml
odoo/addons/ssi_psychology_evaluation/data/ir_sequence_data.xml
odoo/addons/ssi_psychology_evaluation/data/policy_template_data.xml
odoo/addons/ssi_psychology_evaluation/data/sequence_template_data.xml
odoo/addons/ssi_psychology_evaluation/demo/psychology_evaluation_deadline_demo.xml
odoo/addons/ssi_psychology_evaluation/demo/psychology_evaluation_purpose_demo.xml
odoo/addons/ssi_psychology_evaluation/demo/psychology_evaluation_report_type_demo.xml
odoo/addons/ssi_psychology_evaluation/demo/psychology_evaluation_result_demo.xml
odoo/addons/ssi_psychology_evaluation/demo/psychology_evaluation_type_demo.xml
odoo/addons/ssi_psychology_evaluation/demo/psychology_psychogram_demo.xml
odoo/addons/ssi_psychology_evaluation/demo/psychology_psychogram_item_value_demo.xml
odoo/addons/ssi_psychology_evaluation/demo/psychology_psychogram_item_value_set_demo.xml
odoo/addons/ssi_psychology_evaluation/models/__init__.py
odoo/addons/ssi_psychology_evaluation/models/psychology_evaluation.py
odoo/addons/ssi_psychology_evaluation/models/psychology_evaluation_batch.py
odoo/addons/ssi_psychology_evaluation/models/psychology_evaluation_deadline.py
odoo/addons/ssi_psychology_evaluation/models/psychology_evaluation_detail.py
odoo/addons/ssi_psychology_evaluation/models/psychology_evaluation_purpose.py
odoo/addons/ssi_psychology_evaluation/models/psychology_evaluation_recommendation.py
odoo/addons/ssi_psychology_evaluation/models/psychology_evaluation_report_type.py
odoo/addons/ssi_psychology_evaluation/models/psychology_evaluation_result.py
odoo/addons/ssi_psychology_evaluation/models/psychology_evaluation_type.py
odoo/addons/ssi_psychology_evaluation/models/psychology_psychogram.py
odoo14_addon_ssi_psychology_evaluation-14.0.2.8.0.dist-info/METADATA
odoo14_addon_ssi_psychology_evaluation-14.0.2.8.0.dist-info/WHEEL
odoo14_addon_ssi_psychology_evaluation-14.0.2.8.0.dist-info/top_level.txt
odoo14_addon_ssi_psychology_evaluation-14.0.2.8.0.dist-info/RECORD
